{
    "CommandsExportPlaylists": "Here are the playlists!",
    "CommandsChangePlaylist": "The playlist was changed to **%PLAYLIST%**.",
    "CommandsExportPlaylistContentForgotPlaylist": "You forgot to select a playlist!",
    "CommandsExportPlaylistContentNotFound": "Sorry, this playlist doesn't exist. Use the autocomplete feature to select your playlist!",
    "CommandsExportPlaylistContentFound": "Here is the song list! Have fun with it.",
    "CommandsGetSongHistoryForgotDate": "You forgot to add a date!",
    "CommandsGetSongHistoryWrongDate": "You entered a wrong date - remember: YYYY-MM-DD !",
    "CommandsGetSongHistoryNoOpening": "The station wasn't online at that date'.",
    "CommandsGetSongHistoryTooEarly": "You can only go back up to 14 days.",
    "CommandsGetSongHistoryHistoryFound": "Here is the song list! Have fun with it.",
    "CommandsFindSongForgotSong": "You forgot to add a song name!",
    "CommandsFavoriteSongForgotUser": "You forgot to select a user!",
    "CommandsForceCacheRefresh": "The cache was successfully refreshed!",
    "EmbedMusicStatsTitle": "AzuraCast Resource Usage",
    "EmbedMusicStatsPingTitle": "Ping",
    "EmbedMusicStatsPingDesc": "**%VALUE%** ms",
    "EmbedMusicStatsCpuUsageTitle": "CPU usage",
    "EmbedMusicStatsCpuUsageAll": "Total: **%VALUE%**%",
    "EmbedMusicStatsCpuUsageCore": "Core %COUNTER%: **%VALUE%**%\n",
    "EmbedMusicStats1MinLoadTitle": "1-Min-Load",
    "EmbedMusicStats1MinLoadDesc": "**%VALUE%**",
    "EmbedMusicStats5MinLoadTitle": "5-Min-Load",
    "EmbedMusicStats5MinLoadDesc": "**%VALUE%**",
    "EmbedMusicStats15MinLoadTitle": "15-Min-Load",
    "EmbedMusicStats15MinLoadDesc": "**%VALUE%**",
    "EmbedMusicStatsRamUsageTitle": "RAM usage",
    "EmbedMusicStatsRamUsageDesc": "Used: **%USED%** GB\nCached: **%CACHED%** GB\nTotal used: **%TUSED%** GB\nTotal available: **%TOTAL%** GB",
    "EmbedMusicStatsDiskUsageTitle": "Disk usage",
    "EmbedMusicStatsDiskUsageDesc": "Used: **%USED%** GB\nTotal: **%TOTAL%** GB",
    "EmbedMusicStatsNetworkUsageTitle": "Network \"%NAME%\"",
    "EmbedMusicStatsNetworkUsageDesc": "Receive: **%RECEIVE%** KB/s\nTransmit: **%TRANSMIT%** KB/s",
    "EmbedServerIsOfflineTitle": "AzuraCast Is Offline!",
    "EmbedServerIsOnlineTitle": "AzuraCast Is Back Online!",
    "EmbedServerNotAvailableTitle": "Connection Issues",
    "EmbedServerNotAvailableDesc": "AzuraCast is currently not available!",
    "EmbedFilesChangedTitle": "Changes On The File Server Happened!",
    "EmbedFilesAddedSingle": "**One** file was added",
    "EmbedFilesAddedMulti": "**%NUMBER%** files were added",
    "EmbedFilesRemovedSingle": "**One** file was removed",
    "EmbedFilesRemovedMulti": "**%NUMBER%** files were removed",
    "EmbedAzuraUpdateTitle": "AzuraCast Needs To Be Updated!",
    "EmbedAzuraUpdateDesc": "Your AzuraCast installation needs an update. In total: **%NUMBER%**",
    "EmbedAzuraUpdateCurrentRelease": "Current installed version",
    "EmbedAzuraUpdateLatestRelease": "Latest release version",
    "EmbedAzuraUpdateMajorReleaseTitle": "Release update needed?",
    "EmbedAzuraUpdateMajorReleaseDesc": "Yes",
    "EmbedAzuraUpdateSwitchTitle": "Switch to stable branch?",
    "EmbedAzuraUpdateSwitchDesc": "Available without a reinstall!",
    "EmbedAzuraUpdatesTooBig": "Changelog can't be displayed because it's too big.\nCheck it out here: %URL%",
    "EmbedAzuraUpdateChangelogPart": "Changelog part %NUMBER%",
    "EmbedAzuraUpdateChangelog": "Changelog",
    "EmbedAzuraPlaylistChangesTitle": "Action Not Allowed",
    "EmbedAzuraPlaylistChangesDesc": "Playlist changes are currently not allowed!",
    "EmbedAzuraSongRequestsTitle": "Action Not Allowed",
    "EmbedAzuraSongRequestsDesc": "Song requests are currently not allowed!",
    "EmbedAzuraSongInQueueTitle": "Song Is Already In Queue Or Played Already",
    "EmbedAzuraSongInQueueDesc": "This song can't be requested because it's already in the queue or it was played too recently!",
    "EmbedAzuraNowPlayingTitle": "Now Playing",
    "EmbedAzuraNowPlayingSong": "Song",
    "EmbedAzuraNowPlayingArtist": "By",
    "EmbedAzuraNowPlayingAlbum": "On",
    "EmbedAzuraNowPlayingStreamMessage": "Currently served *live* by the one and only **%NAME%**!",
    "EmbedAzuraNowPlayingStreamSince": "Streaming live since",
    "EmbedAzuraNowPlayingDuration": "Duration",
    "EmbedAzuraNowPlayingFooterClosed": "Currently we're closed. Check back later!",
    "EmbedAzuraNowPlayingPlaylist": "Playlist",
    "EmbedAzuraNowPlayingSlogan": "Slogan",
    "EmbedAzuraSearchSongRequestsTitle": "Song Request",
    "EmbedAzuraSearchSongRequestsAvaDesc": "The requested song is available!",
    "EmbedAzuraSearchSongRequestsAvaSong": "Song",
    "EmbedAzuraSearchSongRequestsAvaArtist": "By",
    "EmbedAzuraSearchSongRequestsAvaAlbum": "On",
    "EmbedAzuraSearchSongRequestsFoundDesc": "It wasn't clear what song you requested!\nNow I'll show you some, maybe even the desired one.",
    "EmbedAzuraSearchSongRequestsFoundSong": "Song",
    "EmbedAzuraSearchSongRequestsFoundArtist": "By",
    "EmbedAzuraSearchSongRequestsFoundAlbum": "On",
    "EmbedAzuraSearchSongRequestsFoundAlbumNotAvailable": "Album not available",
    "EmbedAzuraSearchSongRequestsFoundFooter": "Please use for the next search the title and the artist name!",
    "EmbedAzuraSearchSongRequestsNotDesc": "The requested song is sadly not available!",
    "EmbedAzuraSearchSongRequestsNotFooter": "Don't worry, we're already informed!",
    "EmbedAzuraSearchSongRequestsNotAvaTitle": "Requested Song not available!",
    "EmbedAzuraSearchSongRequestsNotAvaDesc": "%NAME% requested a song but it's not available.",
    "EmbedAzuraSearchSongRequestsNotAvaSong": "Song",
    "EmbedAzuraSearchSongRequestsNotAvaArtist": "By",
    "EmbedAzuraSearchSongRequestsRequestTitle": "Song Request",
    "EmbedAzuraSearchSongRequestsRequestDesc": "Your song has been requested!",
    "EmbedAzuraSearchSongRequestsRequestSong": "Song",
    "EmbedAzuraSearchSongRequestsRequestArtist": "By",
    "EmbedAzuraSearchSongRequestsRequestAlbum": "On",
    "EmbedAzuraFavoriteSongTitle": "%NAME% requested a favorite song",
    "EmbedAzuraFavoriteSongDescIsUser": "Have fun with it while it plays!",
    "EmbedAzuraFavoriteSongDescIsNot": "Hey, %NAME%, do you hear that?\nIt's your damn favourite song!\n\nGet yourself online to hear it!",
    "EmbedAzuraFavoriteSongSong": "Song",
    "EmbedAzuraFavoriteSongArtist": "By",
    "EmbedAzuraFavoriteSongAlbum": "On",
    "EmbedAzuraFavoriteSongAlbumNotAvailable": "Album not available"
}
